CSGT/__init__.py
CSGT/model.py
CSGT-1.0.3.dist-info/LICENSE
CSGT-1.0.3.dist-info/METADATA
CSGT-1.0.3.dist-info/WHEEL
CSGT-1.0.3.dist-info/top_level.txt
CSGT-1.0.3.dist-info/RECORD
