Metadata-Version: 2.1
Name: CSGT
Version: 1.0.3
Summary: A deep learning library for Self-Organizing Maps (SOM) with clustering and gradient optimization.
Home-page: https://github.com/MM21B038/CSGO
Author: Manav Gupta
Author-email: manav26102002@gmail.com
Classifier: Programming Language :: Python :: 3
Classifier: License :: OSI Approved :: MIT License
Classifier: Operating System :: OS Independent
Requires-Python: >=3.10
License-File: LICENSE
Requires-Dist: numpy==1.26.4
Requires-Dist: matplotlib==3.7.2
Requires-Dist: scipy==1.11.2
Provides-Extra: dev
Requires-Dist: jupyter; extra == "dev"
Requires-Dist: ipython; extra == "dev"
Requires-Dist: pytest; extra == "dev"
Requires-Dist: flake8; extra == "dev"
